convictquandary/__init__.py
convictquandary/constants.py
convictquandary/game.py
convictquandary/player.py
convictquandary/strategy.py
convictquandary/strategy_filter.py
convictquandary/tournament.py
convictquandary/utils.py
convictquandary/strategies/__init__.py
convictquandary/strategies/alternator.py
convictquandary/strategies/cooperator.py
convictquandary/strategies/davis.py
convictquandary/strategies/defector.py
convictquandary/strategies/grofman.py
convictquandary/strategies/grudger.py
convictquandary/strategies/random.py
convictquandary/strategies/titfortat.py
convictquandary/strategies/tullock.py
convictquandary-0.0.6.dist-info/METADATA
convictquandary-0.0.6.dist-info/WHEEL
convictquandary-0.0.6.dist-info/licenses/LICENSE
convictquandary-0.0.6.dist-info/RECORD
