Metadata-Version: 2.3
Name: convictquandary
Version: 0.0.6
Summary: A extension of the iterated prisoners dilemma tournaments by Axelrod
Project-URL: Homepage, https://github.com/prashant94/convict_quandary
Project-URL: Issues, https://github.com/prashant94/convict_quandary/issues
Author-email: Prashant Sinha <prashantsinha94@gmail.com>
License: MIT License
License-File: LICENSE
Keywords: axelrod,game theory,ipd,iterated prisoners dilemma,prisoners dilemma
Classifier: Development Status :: 1 - Planning
Classifier: Framework :: Flake8
Classifier: Framework :: Matplotlib
Classifier: Framework :: Pytest
Classifier: Intended Audience :: Developers
Classifier: Intended Audience :: Science/Research
Classifier: License :: OSI Approved :: MIT License
Classifier: Operating System :: Microsoft :: Windows
Classifier: Operating System :: OS Independent
Classifier: Programming Language :: Python :: 3
Classifier: Programming Language :: Python :: 3.9
Classifier: Programming Language :: Python :: 3.10
Classifier: Programming Language :: Python :: 3.11
Classifier: Programming Language :: Python :: 3.12
Requires-Python: >=3.9
